{
  "generated_at": "2025-12-19T04:25:22.758588",
  "channels": [
    {
      "channel_id": "UCPej5ow_Y4MAoRQlnoBcGjg",
      "title": "Motsov Воронеж",
      "description": "89009603648 Артём / покупка мототехники СССР / г.Воронеж ",
      "published_at": "2018-12-09T11:54:34Z",
      "country": "N/A",
      "subscribers": 22100,
      "views": 10818801,
      "videos": 428,
      "uploads_playlist": "UUPej5ow_Y4MAoRQlnoBcGjg",
      "timestamp": "2025-12-19T04:25:22.469916",
      "handle": "shum_motora"
    }
  ],
  "recent_videos": [
    {
      "video_id": "hTxlagx7594",
      "title": "Декоративная накладка замка зажигания Иж Урал Днепр К750 #motsov #моторазбор #иж #урал #днепр",
      "published_at": "2025-12-18T07:00:40Z",
      "duration": "PT1M1S",
      "views": 1142,
      "likes": 22,
      "comments": 0,
      "channel_id": "UCPej5ow_Y4MAoRQlnoBcGjg",
      "channel_title": "Motsov Воронеж"
    },
    {
      "video_id": "8j0Bt2D2tAw",
      "title": "Готово! Двигатель Голубого Огонька на своём законном месте #motsov #моторазбор #воронеж #иж",
      "published_at": "2025-12-17T07:00:07Z",
      "duration": "PT47S",
      "views": 5831,
      "likes": 136,
      "comments": 4,
      "channel_id": "UCPej5ow_Y4MAoRQlnoBcGjg",
      "channel_title": "Motsov Воронеж"
    },
    {
      "video_id": "V98DzNjJw98",
      "title": "Дан старт сборки Огонька, достали раму на центр и начинаем #motsov #моторазбор #воронеж #иж #планета",
      "published_at": "2025-12-16T08:10:00Z",
      "duration": "PT1M2S",
      "views": 1860,
      "likes": 65,
      "comments": 4,
      "channel_id": "UCPej5ow_Y4MAoRQlnoBcGjg",
      "channel_title": "Motsov Воронеж"
    },
    {
      "video_id": "nJsYfvx5fZ0",
      "title": "Три интересные запчасти за последний месяц #motsov #моторазбор #воронеж #иж #урал #минск #восход",
      "published_at": "2025-12-15T07:22:24Z",
      "duration": "PT1M15S",
      "views": 7851,
      "likes": 99,
      "comments": 1,
      "channel_id": "UCPej5ow_Y4MAoRQlnoBcGjg",
      "channel_title": "Motsov Воронеж"
    },
    {
      "video_id": "tzVUFTkeDHo",
      "title": "Иж Планета 5 в разборе #motsov #моторазбор #воронеж #иж #урал #минск #восход #днепр",
      "published_at": "2025-12-14T08:27:06Z",
      "duration": "PT1M45S",
      "views": 7352,
      "likes": 179,
      "comments": 5,
      "channel_id": "UCPej5ow_Y4MAoRQlnoBcGjg",
      "channel_title": "Motsov Воронеж"
    }
  ]
}